pylet/__init__.py
pylet/_cluster.py
pylet/_instance.py
pylet/_state.py
pylet/_sync_api.py
pylet/_worker_info.py
pylet/cli.py
pylet/client.py
pylet/config.py
pylet/config_file.py
pylet/controller.py
pylet/db.py
pylet/errors.py
pylet/log_sidecar.py
pylet/logger.py
pylet/schemas.py
pylet/server.py
pylet/worker.py
pylet/worker_http.py
pylet-0.4.0.dist-info/licenses/LICENSE
pylet-0.4.0.dist-info/METADATA
pylet-0.4.0.dist-info/WHEEL
pylet-0.4.0.dist-info/entry_points.txt
pylet-0.4.0.dist-info/top_level.txt
pylet-0.4.0.dist-info/RECORD
