Metadata-Version: 2.4
Name: pylet
Version: 0.4.0
Summary: A simple distributed task execution system for GPU servers
Author-email: Yao Fu <yao.fu.aisys@gmail.com>
License-Expression: Apache-2.0
Project-URL: Homepage, https://github.com/ServerlessLLM/pylet
Project-URL: Repository, https://github.com/ServerlessLLM/pylet
Project-URL: Issues, https://github.com/ServerlessLLM/pylet/issues
Keywords: distributed,gpu,cluster,task,execution,scheduling
Classifier: Development Status :: 4 - Beta
Classifier: Intended Audience :: Developers
Classifier: Intended Audience :: Science/Research
Classifier: Operating System :: POSIX :: Linux
Classifier: Programming Language :: Python :: 3
Classifier: Programming Language :: Python :: 3.9
Classifier: Programming Language :: Python :: 3.10
Classifier: Programming Language :: Python :: 3.11
Classifier: Programming Language :: Python :: 3.12
Classifier: Programming Language :: Python :: 3.13
Classifier: Topic :: System :: Distributed Computing
Requires-Python: >=3.9
License-File: LICENSE
Requires-Dist: fastapi>=0.100.0
Requires-Dist: uvicorn>=0.20.0
Requires-Dist: httpx>=0.24.0
Requires-Dist: pydantic>=2.0.0
Requires-Dist: click>=8.0.0
Requires-Dist: aiosqlite>=0.19.0
Requires-Dist: aiohttp>=3.8.0
Requires-Dist: tomli>=2.0.0; python_version < "3.11"
Provides-Extra: dev
Requires-Dist: pytest>=7.0.0; extra == "dev"
Requires-Dist: pytest-asyncio>=0.21.0; extra == "dev"
Dynamic: license-file
